icenews/__init__.py
icenews/__main__.py
icenews/api_detect_language.py
icenews/api_edit_distance.py
icenews/api_important_words.py
icenews/api_parse_v1.py
icenews/concepts.py
icenews/server.py
icenews/similar.py
icenews-1.2.1.dist-info/LICENSE
icenews-1.2.1.dist-info/METADATA
icenews-1.2.1.dist-info/WHEEL
icenews-1.2.1.dist-info/entry_points.txt
icenews-1.2.1.dist-info/top_level.txt
icenews-1.2.1.dist-info/RECORD
