Metadata-Version: 2.1
Name: icenews
Version: 1.2.1
Summary: Simple NLP for Icelandic News
Home-page: https://github.com/sverrirab/icenews
Author: Sverrir A. Berg
Author-email: sab@keilir.com
License: Apache
Keywords: nlp,icelandic
Platform: UNKNOWN
Classifier: Development Status :: 3 - Alpha
Classifier: License :: OSI Approved :: Apache Software License
Classifier: Intended Audience :: Developers
Classifier: Operating System :: OS Independent
Classifier: Programming Language :: Python
Classifier: Programming Language :: Python :: 3
Classifier: Programming Language :: Python :: 3.6
Classifier: Programming Language :: Python :: 3.7
Classifier: Topic :: Software Development :: Libraries :: Python Modules
Requires-Dist: fastapi (==0.61.1)
Requires-Dist: nltk (==3.5)
Requires-Dist: pycld2 (==0.41)
Requires-Dist: pydantic (==1.6.1)
Requires-Dist: reynir (==2.7.0)
Requires-Dist: uvicorn (==0.12.2)
